papirus/__init__.py
papirus/composite.py
papirus/epd.py
papirus/image.py
papirus/lm75b.py
papirus/readrtc.py
papirus/text.py
papirus/textpos.py
papirus-1.0.0.data/data/bitmaps/0.gif
papirus-1.0.0.data/data/bitmaps/1.gif
papirus-1.0.0.data/data/bitmaps/10.gif
papirus-1.0.0.data/data/bitmaps/11.gif
papirus-1.0.0.data/data/bitmaps/12.gif
papirus-1.0.0.data/data/bitmaps/13.gif
papirus-1.0.0.data/data/bitmaps/14.gif
papirus-1.0.0.data/data/bitmaps/15.gif
papirus-1.0.0.data/data/bitmaps/2.gif
papirus-1.0.0.data/data/bitmaps/3.gif
papirus-1.0.0.data/data/bitmaps/4.gif
papirus-1.0.0.data/data/bitmaps/5.gif
papirus-1.0.0.data/data/bitmaps/6.gif
papirus-1.0.0.data/data/bitmaps/7.gif
papirus-1.0.0.data/data/bitmaps/8.gif
papirus-1.0.0.data/data/bitmaps/9.gif
papirus-1.0.0.data/data/bitmaps/papirus-cam-intro.jpg
papirus-1.0.0.data/data/bitmaps/papirus-logo.bmp
papirus-1.0.0.data/data/bitmaps/python.png
papirus-1.0.0.data/scripts/papirus-animation
papirus-1.0.0.data/scripts/papirus-buttons
papirus-1.0.0.data/scripts/papirus-cam
papirus-1.0.0.data/scripts/papirus-clear
papirus-1.0.0.data/scripts/papirus-clock
papirus-1.0.0.data/scripts/papirus-composite-write
papirus-1.0.0.data/scripts/papirus-config
papirus-1.0.0.data/scripts/papirus-draw
papirus-1.0.0.data/scripts/papirus-fbcopy
papirus-1.0.0.data/scripts/papirus-gol
papirus-1.0.0.data/scripts/papirus-radar
papirus-1.0.0.data/scripts/papirus-set
papirus-1.0.0.data/scripts/papirus-setup
papirus-1.0.0.data/scripts/papirus-snake
papirus-1.0.0.data/scripts/papirus-system
papirus-1.0.0.data/scripts/papirus-temp
papirus-1.0.0.data/scripts/papirus-test
papirus-1.0.0.data/scripts/papirus-textfill
papirus-1.0.0.data/scripts/papirus-twitter
papirus-1.0.0.data/scripts/papirus-write
papirus-1.0.0.dist-info/LICENSE.md
papirus-1.0.0.dist-info/METADATA
papirus-1.0.0.dist-info/WHEEL
papirus-1.0.0.dist-info/top_level.txt
papirus-1.0.0.dist-info/RECORD
