Metadata-Version: 2.1
Name: papirus
Version: 1.0.0
Summary: PaPiRus API
Home-page: https://pi-supply.com
Author: PiSupply
Author-email: sales@pi-supply.com
Project-URL: Bug Tracker, https://github.com/PiSupply/PaPiRus/issues
License-File: LICENSE.md
